fvhzdtcsrfxcrddsrxe/__init__.py
fvhzdtcsrfxcrddsrxe/__main__.py
fvhzdtcsrfxcrddsrxe-0.0.0.dist-info/LICENSE.txt
fvhzdtcsrfxcrddsrxe-0.0.0.dist-info/METADATA
fvhzdtcsrfxcrddsrxe-0.0.0.dist-info/WHEEL
fvhzdtcsrfxcrddsrxe-0.0.0.dist-info/top_level.txt
fvhzdtcsrfxcrddsrxe-0.0.0.dist-info/RECORD
