Metadata-Version: 2.1
Name: fvhzdtcsrfxcrddsrxe
Version: 0.0.0
Summary: fvhzdtcsrfxcrddsrxe
Author-email: Aaron Alphabet <aaron.alphabet@posteo.org>
License: The MIT License (MIT)
Classifier: License :: OSI Approved :: MIT License
Classifier: Programming Language :: Python
Classifier: Programming Language :: Python :: 3
Requires-Python: >=3.11
License-File: LICENSE.txt
